move2archive/__init__.py
move2archive-2023.7.15.1.dist-info/METADATA
move2archive-2023.7.15.1.dist-info/WHEEL
move2archive-2023.7.15.1.dist-info/entry_points.txt
move2archive-2023.7.15.1.dist-info/top_level.txt
move2archive-2023.7.15.1.dist-info/RECORD
