Metadata-Version: 2.1
Name: move2archive
Version: 2023.7.15.1
Summary: Managing event-related files in a folder hierarchy like <ARCHIVE>/2013/2013-05-17 Event name/
Home-page: https://github.com/novoid/move2archive
Download-URL: https://github.com/novoid/move2archive/zipball/master
Author: Karl Voit
Author-email: tools@Karl-Voit.at
Keywords: file managing,file management,files,date,time,time-stamps
Classifier: Programming Language :: Python :: 3 :: Only
Classifier: Development Status :: 5 - Production/Stable
Classifier: Environment :: Console
Classifier: Intended Audience :: End Users/Desktop
Classifier: License :: OSI Approved :: GNU General Public License (GPL)
Classifier: Operating System :: OS Independent
Requires-Dist: pyreadline
